{"cameraMode":{"drawMode":0,"name":"Shaded","section":"Shading Mode"},"sceneLighting":true,"audioPlay":false,"sceneViewState":{"m_AlwaysRefresh":false,"showFog":true,"showSkybox":true,"showFlares":true,"showImageEffects":true,"showParticleSystems":true,"showVisualEffectGraphs":true,"m_FxEnabled":true},"in2DMode":false,"pivot":{"x":13.797148704528809,"y":3.597525119781494,"z":0.929544985294342},"rotation":{"x":0.0021427422761917116,"y":-0.4415687024593353,"z":0.0010567689314484597,"w":0.8969001770019531},"size":11.190917015075684,"orthographic":false}